batch_router/__init__.py
batch_router/core/__init__.py
batch_router/core/base/__init__.py
batch_router/core/base/batch.py
batch_router/core/base/content.py
batch_router/core/base/modality.py
batch_router/core/base/provider.py
batch_router/core/base/request.py
batch_router/core/input/__init__.py
batch_router/core/input/batch.py
batch_router/core/input/message.py
batch_router/core/input/request.py
batch_router/core/input/role.py
batch_router/core/output/__init__.py
batch_router/core/output/batch.py
batch_router/core/output/message.py
batch_router/core/output/request.py
batch_router/core/output/role.py
batch_router/providers/__init__.py
batch_router/providers/anthropic/__init__.py
batch_router/providers/anthropic/anthropic_provider.py
batch_router/providers/base/__init__.py
batch_router/providers/base/base_provider.py
batch_router/providers/base/batch_provider.py
batch_router/providers/base/stream_provider.py
batch_router/providers/google/__init__.py
batch_router/providers/google/google_genai_models.py
batch_router/providers/google/google_genai_provider.py
batch_router/providers/openai/__init__.py
batch_router/providers/openai/chat_completions_models.py
batch_router/providers/openai/common_models.py
batch_router/providers/openai/openai_chat_completions_provider.py
batch_router/providers/openai/openai_responses_provider.py
batch_router/providers/openai/responses_models.py
batch_router/providers/vllm/__init__.py
batch_router/providers/vllm/vllm_provider.py
batch_router/utilities/mime_type.py
batch_router-0.2.6.dist-info/WHEEL
batch_router-0.2.6.dist-info/METADATA
batch_router-0.2.6.dist-info/RECORD
