Metadata-Version: 2.3
Name: batch-router
Version: 0.2.6
Summary: A Python package designed to facilitate batch LLM requests efficiently across multiple providers with a unified interface.
Author: javi22020
Author-email: javi22020 <90896750+javi22020@users.noreply.github.com>
Requires-Dist: anthropic>=0.71.0
Requires-Dist: filetype>=1.2.0
Requires-Dist: google-genai>=1.51.0
Requires-Dist: openai>=2.8.0
Requires-Dist: psutil>=7.1.3
Requires-Dist: requests>=2.32.5
Requires-Dist: tiktoken>=0.12.0
Requires-Dist: numpy>=2.0.2
Requires-Dist: pandas>=2.3.3 ; extra == 'evals'
Requires-Python: >=3.10
Provides-Extra: evals
